{
    "backend": "django",
    "db_name": "",
    "db_pass": "",
    "db_type": "mysql",
    "db_user": "",
    "dbms": "1",
    "description": "generated product",
    "design": "soft-ui-dashboard",
    "docker": "0",
    "err_code": 0,
    "frontend": "",
    "heroku": "0",
    "pattern": "mvc",
    "pro": "0",
    "task_id": "27cc5403-85ee-4020-bbf8-4f009d8b3424",
    "task_info": "Upload Sources [0%] - 347 files",
    "task_output": "27cc5403-85ee-4020-bbf8-4f009d8b3424.zip",
    "task_result": "SUCCESS",
    "task_state": "RUNNING",
    "task_ts_end": "2022-11-21-19-28-18",
    "task_ts_start": "2022-11-21-19-28-15"
}